dynadbmutex
