Metadata-Version: 1.1
Name: dynadbmutex
Version: 0.0.6
Summary: A simple mutex implementation on top of DynamoDB.
Home-page: https://github.com/erwan-lemonnier/dynamodbmutex
Author: Erwan Lemonnier
Author-email: erwan@lemonnier.se
License: BSD
Platform: any
Classifier: Environment :: Web Environment
Classifier: Intended Audience :: Developers
Classifier: License :: OSI Approved :: BSD License
Classifier: Operating System :: OS Independent
Classifier: Programming Language :: Python
Classifier: Topic :: Internet :: WWW/HTTP :: Dynamic Content
Classifier: Topic :: Software Development :: Libraries :: Python Modules
